ua_project_transfer/__init__.py
ua_project_transfer/core_specifics_template.py
ua_project_transfer/log_config_template.py
ua_project_transfer/next_steps_template.py
ua_project_transfer/post_containers_batch_template.xml
ua_project_transfer/post_containers_template.xml
ua_project_transfer/post_project_template.xml
ua_project_transfer/post_researcher_template.xml
ua_project_transfer/post_samples_batch_template.xml
ua_project_transfer/post_samples_template.xml
ua_project_transfer/price_check_template.py
ua_project_transfer/project_lims_tools.py
ua_project_transfer/project_transfer.py
ua_project_transfer/wf_steps_template.py
ua_project_transfer-1.1.8.dist-info/LICENSE
ua_project_transfer-1.1.8.dist-info/METADATA
ua_project_transfer-1.1.8.dist-info/WHEEL
ua_project_transfer-1.1.8.dist-info/top_level.txt
ua_project_transfer-1.1.8.dist-info/RECORD
