Metadata-Version: 2.1
Name: ua-project-transfer
Version: 1.1.8
Summary: Converts iLab service requests to Illumina Clarity Projects.
Home-page: https://github.com/UACoreFacilitiesIT/UA-Project-Transfer
Author: Stephen Stern, Rafael Lopez, Etienne Thompson
Author-email: sterns1@email.arizona.edu
License: MIT
Platform: UNKNOWN
Requires-Dist: bs4
Requires-Dist: lxml
Requires-Dist: requests
Requires-Dist: ua-stache-api
Requires-Dist: ua-clarity-tools
Requires-Dist: ua-ilab-tools
